LICENSE
p115rsacipher/__init__.py
p115rsacipher/py.typed
p115rsacipher-0.0.1.dist-info/LICENSE
p115rsacipher-0.0.1.dist-info/METADATA
p115rsacipher-0.0.1.dist-info/WHEEL
p115rsacipher-0.0.1.dist-info/RECORD
